chattr_event_bus/__init__.py
chattr_event_bus/constants/__init__.py
chattr_event_bus/constants/schema.py
chattr_event_bus/consumers/subscribers.py
chattr_event_bus/schemas/analytics/analytics.event_ingress_v1.schema.json
chattr_event_bus/schemas/campaign_engine/CETopic_v100.schema.json
chattr_event_bus/schemas/conversation_engine/conversation_portal.ws.send_v100.schema.json
chattr_event_bus/schemas/ecommerce/browser.event_mapping_v1.schema.json
chattr_event_bus/schemas/ecommerce/historical.order.received_v1.schema.json
chattr_event_bus/schemas/ecommerce/order.received2_v1.schema.json
chattr_event_bus/schemas/ecommerce/order.received_v1.schema.json
chattr_event_bus/schemas/ecommerce/shopify.cart_event_v1.schema.json
chattr_event_bus/schemas/ecommerce/shopify.checkout_v1.schema.json
chattr_event_bus/schemas/ecommerce/shopify.order_v1.schema.json
chattr_event_bus/schemas/ecommerce_subscription_engine/subscription.received_v1.schema.json
chattr_event_bus/schemas/general/GeneralTopic_v1.schema.json
chattr_event_bus/schemas/lists/klaviyo.update_v1.schema.json
chattr_event_bus/schemas/messaging/messaging.incoming_message_v1.schema.json
chattr_event_bus/schemas/messaging/messaging.outgoing_message_v1.schema.json
chattr_event_bus/schemas/sample_product/SampleTopic_v1.schema.json
chattr_event_bus/schemas/sample_product/SampleTopic_v2.schema.json
chattr_event_bus/schemas/segment/segment.calculate_user_counts_v1.schema.json
chattr_event_bus/schemas/segment/segment.sync_elastic_search_v1.schema.json
chattr_event_bus/schemas/sensus/SensusTopic_v100.schema.json
chattr_event_bus/schemas/subscriber_engine/SubscriberEngineTopic_v100.schema.json
chattr_event_bus/schemas/subscriptions/Subscriptions.schema.json
chattr_event_bus/schemas/test/TestTopic_v100.schema.json
chattr_event_bus/schemas/test/TestTopic_v101.schema.json
chattr_event_bus/schemas/vaportal/VATopic_v100.schema.json
chattr_event_bus/schemas/vaportal/ws.send.event_schemas_v100.schema.json
chattr_event_bus-0.1.0.dist-info/WHEEL
chattr_event_bus-0.1.0.dist-info/METADATA
chattr_event_bus-0.1.0.dist-info/RECORD
