Metadata-Version: 2.1
Name: chattr-event-bus
Version: 0.1.0
Summary: 
Author: Chattr
Author-email: chattr23@gmail.com
Requires-Python: >=3.8,<4.0
Classifier: Programming Language :: Python :: 3
Classifier: Programming Language :: Python :: 3.10
Classifier: Programming Language :: Python :: 3.8
Classifier: Programming Language :: Python :: 3.9
Requires-Dist: chattr-config (==0.1.1)
Requires-Dist: faust-streaming (>=0.10.4,<0.11.0)
Requires-Dist: jsonschema (==4.17.3)
Requires-Dist: pytz (>=2022.7.1,<2023.0.0)
